pyajax/__init__.py
pyajax-0.0.6.dist-info/METADATA
pyajax-0.0.6.dist-info/RECORD
pyajax-0.0.6.dist-info/WHEEL
pyajax-0.0.6.dist-info/top_level.txt
